{
  "project_info": {
    "project_number": "985699580751",
    "project_id": "weather-forecast-b045c",
    "storage_bucket": "weather-forecast-b045c.appspot.com"
  },
  "client": [
    {
      "client_info": {
        "mobilesdk_app_id": "1:985699580751:android:f3cc1acf75ddd0d759633a",
        "android_client_info": {
          "package_name": "ustun.muharrem.weatherforecast"
        }
      },
      "oauth_client": [
        {
          "client_id": "985699580751-j4iev6etflgoma0nh7n4h962qauim1q5.apps.googleusercontent.com",
          "client_type": 3
        }
      ],
      "api_key": [
        {
          "current_key": "AIzaSyAdD7gV7cdKjEolLtxUM2FiX4a-IWCWYhg"
        }
      ],
      "services": {
        "appinvite_service": {
          "other_platform_oauth_client": [
            {
              "client_id": "985699580751-j4iev6etflgoma0nh7n4h962qauim1q5.apps.googleusercontent.com",
              "client_type": 3
            }
          ]
        }
      }
    }
  ],
  "configuration_version": "1"
}